// Attempt #2 javap -c -p DeadlockExample >> output.txt
Compiled from "DeadLockExample.java"
public class Deadlock.DeadLockExample {
  private static final java.lang.Object lock1;

  private static final java.lang.Object lock2;

  public Deadlock.DeadLockExample();
    Code:
         0: aload_0
         1: invokespecial #1                  // Method java/lang/Object."<init>":()V
         4: return

  public static void main(java.lang.String[]);
    Code:
         0: new           #7                  // class java/lang/Thread
         3: dup
         4: invokedynamic #9,  0              // InvokeDynamic #0:run:()Ljava/lang/Runnable;
         9: invokespecial #13                 // Method java/lang/Thread."<init>":(Ljava/lang/Runnable;)V
        12: astore_1
        13: new           #7                  // class java/lang/Thread
        16: dup
        17: invokedynamic #16,  0             // InvokeDynamic #1:run:()Ljava/lang/Runnable;
        22: invokespecial #13                 // Method java/lang/Thread."<init>":(Ljava/lang/Runnable;)V
        25: astore_2
        26: aload_1
        27: invokevirtual #17                 // Method java/lang/Thread.start:()V
        30: aload_2
        31: invokevirtual #17                 // Method java/lang/Thread.start:()V
        34: return

  private static void lambda$main$1();
    Code:
         0: getstatic     #20                 // Field java/lang/System.out:Ljava/io/PrintStream;
         3: ldc           #26                 // String Thread 2: Trying to acquire lock2
         5: invokevirtual #28                 // Method java/io/PrintStream.println:(Ljava/lang/String;)V
         8: getstatic     #34                 // Field lock2:Ljava/lang/Object;
        11: dup
        12: astore_0
        13: monitorenter
        14: getstatic     #20                 // Field java/lang/System.out:Ljava/io/PrintStream;
        17: ldc           #40                 // String Thread 2: Acquired lock2
        19: invokevirtual #28                 // Method java/io/PrintStream.println:(Ljava/lang/String;)V
        22: ldc2_w        #42                 // long 100l
        25: invokestatic  #44                 // Method java/lang/Thread.sleep:(J)V
        28: goto          38
        31: astore_1
        32: invokestatic  #50                 // Method java/lang/Thread.currentThread:()Ljava/lang/Thread;
        35: invokevirtual #54                 // Method java/lang/Thread.interrupt:()V
        38: getstatic     #20                 // Field java/lang/System.out:Ljava/io/PrintStream;
        41: ldc           #57                 // String Thread 2: Waiting to acquire lock1
        43: invokevirtual #28                 // Method java/io/PrintStream.println:(Ljava/lang/String;)V
        46: getstatic     #59                 // Field lock1:Ljava/lang/Object;
        49: dup
        50: astore_1
        51: monitorenter
        52: getstatic     #20                 // Field java/lang/System.out:Ljava/io/PrintStream;
        55: ldc           #62                 // String Thread 2: Acquired lock1
        57: invokevirtual #28                 // Method java/io/PrintStream.println:(Ljava/lang/String;)V
        60: aload_1
        61: monitorexit
        62: goto          70
        65: astore_2
        66: aload_1
        67: monitorexit
        68: aload_2
        69: athrow
        70: aload_0
        71: monitorexit
        72: goto          80
        75: astore_3
        76: aload_0
        77: monitorexit
        78: aload_3
        79: athrow
        80: return
      Exception table:
         from    to  target type
            22    28    31   Class java/lang/InterruptedException
            52    62    65   any
            65    68    65   any
            14    72    75   any
            75    78    75   any

  private static void lambda$main$0();
    Code:
         0: getstatic     #20                 // Field java/lang/System.out:Ljava/io/PrintStream;
         3: ldc           #64                 // String Thread 1: Trying to acquire lock1
         5: invokevirtual #28                 // Method java/io/PrintStream.println:(Ljava/lang/String;)V
         8: getstatic     #59                 // Field lock1:Ljava/lang/Object;
        11: dup
        12: astore_0
        13: monitorenter
        14: getstatic     #20                 // Field java/lang/System.out:Ljava/io/PrintStream;
        17: ldc           #66                 // String Thread 1: Acquired lock1
        19: invokevirtual #28                 // Method java/io/PrintStream.println:(Ljava/lang/String;)V
        22: ldc2_w        #42                 // long 100l
        25: invokestatic  #44                 // Method java/lang/Thread.sleep:(J)V
        28: goto          38
        31: astore_1
        32: invokestatic  #50                 // Method java/lang/Thread.currentThread:()Ljava/lang/Thread;
        35: invokevirtual #54                 // Method java/lang/Thread.interrupt:()V
        38: getstatic     #20                 // Field java/lang/System.out:Ljava/io/PrintStream;
        41: ldc           #68                 // String Thread 1: Waiting to acquire lock2
        43: invokevirtual #28                 // Method java/io/PrintStream.println:(Ljava/lang/String;)V
        46: getstatic     #34                 // Field lock2:Ljava/lang/Object;
        49: dup
        50: astore_1
        51: monitorenter
        52: getstatic     #20                 // Field java/lang/System.out:Ljava/io/PrintStream;
        55: ldc           #70                 // String Thread 1: Acquired lock2
        57: invokevirtual #28                 // Method java/io/PrintStream.println:(Ljava/lang/String;)V
        60: aload_1
        61: monitorexit
        62: goto          70
        65: astore_2
        66: aload_1
        67: monitorexit
        68: aload_2
        69: athrow
        70: aload_0
        71: monitorexit
        72: goto          80
        75: astore_3
        76: aload_0
        77: monitorexit
        78: aload_3
        79: athrow
        80: return
      Exception table:
         from    to  target type
            22    28    31   Class java/lang/InterruptedException
            52    62    65   any
            65    68    65   any
            14    72    75   any
            75    78    75   any

  static {};
    Code:
         0: new           #2                  // class java/lang/Object
         3: dup
         4: invokespecial #1                  // Method java/lang/Object."<init>":()V
         7: putstatic     #59                 // Field lock1:Ljava/lang/Object;
        10: new           #2                  // class java/lang/Object
        13: dup
        14: invokespecial #1                  // Method java/lang/Object."<init>":()V
        17: putstatic     #34                 // Field lock2:Ljava/lang/Object;
        20: return
}